{
    "summary": {
        "compliant": 0,
        "warnings": 0,
        "errors": 1,
        "total_files": 1
    },
    "files": [
        {
            "name": "comprehensive_test.php",
            "path": "\/mnt\/c\/wamp64\/www\/php_optimizer\/src\/Services\/..\/..\/storage\/uploads\/comprehensive_test_1758400438_d5cf8a63c220d1a7.php",
            "status": "error",
            "issues": [
                {
                    "severity": "warning",
                    "message": "Possible effet de bord détecté (output)",
                    "line": 1,
                    "rule": "PSR-1.side_effects",
                    "suggestion": "Évitez les sorties directes dans les fichiers de classe"
                },
                {
                    "severity": "info",
                    "message": "Espaces en fin de ligne",
                    "line": 8,
                    "rule": "PSR-2.trailing_whitespace",
                    "suggestion": "Supprimez les espaces en fin de ligne"
                },
                {
                    "severity": "info",
                    "message": "Espaces en fin de ligne",
                    "line": 11,
                    "rule": "PSR-2.trailing_whitespace",
                    "suggestion": "Supprimez les espaces en fin de ligne"
                },
                {
                    "severity": "info",
                    "message": "Espaces en fin de ligne",
                    "line": 15,
                    "rule": "PSR-2.trailing_whitespace",
                    "suggestion": "Supprimez les espaces en fin de ligne"
                },
                {
                    "severity": "warning",
                    "message": "Ligne trop longue (160 caractères)",
                    "line": 17,
                    "rule": "PSR-2.line_length",
                    "suggestion": "Divisez la ligne en plusieurs lignes"
                },
                {
                    "severity": "info",
                    "message": "Espaces en fin de ligne",
                    "line": 18,
                    "rule": "PSR-2.trailing_whitespace",
                    "suggestion": "Supprimez les espaces en fin de ligne"
                },
                {
                    "severity": "error",
                    "message": "Déclaration de namespace manquante",
                    "line": 1,
                    "rule": "PSR-4.namespace",
                    "suggestion": "Ajoutez une déclaration de namespace"
                }
            ],
            "psr_compliance": [
                {
                    "standard": "PSR-1",
                    "compliant": false,
                    "issues_count": 1
                },
                {
                    "standard": "PSR-2",
                    "compliant": false,
                    "issues_count": 5
                },
                {
                    "standard": "PSR-4",
                    "compliant": false,
                    "issues_count": 1
                },
                {
                    "standard": "PSR-12",
                    "compliant": true,
                    "issues_count": 0
                }
            ],
            "metrics": {
                "total_issues": 7,
                "errors": 1,
                "warnings": 2,
                "info": 4
            }
        }
    ]
}